[
    {
        "Id": 0,
        "Color": 0,
        "X": 1,
        "Y": 3
    },
    {
        "Id": 1,
        "Color": 0,
        "X": 1,
        "Y": 3
    },
    {
        "Id": 2,
        "Color": 0,
        "X": 1,
        "Y": 3
    },
    {
        "Id": 3,
        "Color": 0,
        "X": 1,
        "Y": 3
    },
    {
        "Id": 4,
        "Color": 1,
        "X": 9,
        "Y": 1
    },
    {
        "Id": 5,
        "Color": 1,
        "X": 9,
        "Y": 1
    },
    {
        "Id": 6,
        "Color": 1,
        "X": 9,
        "Y": 1
    },
    {
        "Id": 7,
        "Color": 1,
        "X": 9,
        "Y": 1
    },
    {
        "Id": 8,
        "Color": 2,
        "X": 3,
        "Y": 11
    },
    {
        "Id": 9,
        "Color": 2,
        "X": 3,
        "Y": 11
    },
    {
        "Id": 10,
        "Color": 2,
        "X": 3,
        "Y": 11
    },
    {
        "Id": 11,
        "Color": 2,
        "X": 3,
        "Y": 11
    },
    {
        "Id": 12,
        "Color": 3,
        "X": 11,
        "Y": 9
    },
    {
        "Id": 13,
        "Color": 3,
        "X": 11,
        "Y": 9
    },
    {
        "Id": 14,
        "Color": 3,
        "X": 11,
        "Y": 9
    },
    {
        "Id": 15,
        "Color": 3,
        "X": 11,
        "Y": 9
    }
]